Metadata-Version: 1.1
Name: stringfunctions
Version: 0.0.4
Summary: A all in one string function package
Home-page: https://github.com/thanamesleo/stringfunctions
Author: Leonard "thanamesleo" W.
Author-email: jetexer1.yt@gmail.com
License: MIT
Keywords: better,string,stringfunctions,function,setterstrings,string function,Better Strings
Platform: UNKNOWN
Classifier: Development Status :: 5 - Production/Stable
Classifier: Intended Audience :: Education
Classifier: Operating System :: Microsoft :: Windows :: Windows 10
Classifier: License :: OSI Approved :: MIT License
Classifier: Programming Language :: Python :: 3
